{
  "date": "2026-04-22",
  "prices": {
    "ICE": {
      "name": "Intercontinental Exchange",
      "price": 158.63,
      "change_pct": -1.35
    },
    "CRCL": {
      "name": "Circle",
      "price": 96.02,
      "change_pct": -8.94
    },
    "HOOD": {
      "name": "Robinhood",
      "price": 86.43,
      "change_pct": -5.05
    },
    "COIN": {
      "name": "Coinbase",
      "price": 195.95,
      "change_pct": -6.69
    },
    "NDAQ": {
      "name": "Nasdaq",
      "price": 87.6,
      "change_pct": -0.96
    },
    "BK": {
      "name": "BNY Mellon",
      "price": 137.92,
      "change_pct": 2.16
    },
    "FFIV": {
      "name": "F5 Networks",
      "price": 315.56,
      "change_pct": 0.49
    },
    "BLK": {
      "name": "BlackRock",
      "price": 1042.85,
      "change_pct": -0.61
    }
  },
  "news_count": 0,
  "has_update": true
}